pysaba-1.1.0.dist-info/DESCRIPTION.rst
pysaba-1.1.0.dist-info/METADATA
pysaba-1.1.0.dist-info/metadata.json
pysaba-1.1.0.dist-info/RECORD
pysaba-1.1.0.dist-info/top_level.txt
pysaba-1.1.0.dist-info/WHEEL
saba/__init__.py
saba/client.py
saba/exceptions.py
