Metadata-Version: 2.0
Name: pysaba
Version: 1.1.0
Summary: Sabat client library for API management
Home-page: https://github.com/tonybaloney/pysaba
Author: Anthony Shaw
Author-email: anthonyshaw@apache.org
License: Apache License (2.0)
Keywords: sabat
Platform: UNKNOWN
Classifier: Development Status :: 2 - Pre-Alpha
Classifier: Intended Audience :: Developers
Classifier: License :: OSI Approved :: Apache Software License
Classifier: Natural Language :: English
Classifier: Programming Language :: Python :: 2
Classifier: Programming Language :: Python :: 2.6
Classifier: Programming Language :: Python :: 2.7
Classifier: Programming Language :: Python :: 3
Classifier: Programming Language :: Python :: 3.3
Classifier: Programming Language :: Python :: 3.4
Classifier: Programming Language :: Python :: 3.5
Requires-Dist: six
Requires-Dist: requests
Requires-Dist: arrow
